devtools_backslash_escape/__init__.py
devtools_backslash_escape-1.0.1.dist-info/METADATA
devtools_backslash_escape-1.0.1.dist-info/WHEEL
devtools_backslash_escape-1.0.1.dist-info/top_level.txt
devtools_backslash_escape-1.0.1.dist-info/RECORD
