Metadata-Version: 2.1
Name: devtools_backslash_escape
Version: 1.0.1
Summary: Backslash escape/unescape tool
Home-page: https://devtools.at/tools/backslash-escape
Author: DevTools.at
Author-email: hello@devtools.at
Project-URL: Homepage, https://devtools.at/tools/backslash-escape
Project-URL: Repository, https://github.com/devtools-at/backslash-escape
Classifier: Development Status :: 4 - Beta
Classifier: Intended Audience :: Developers
Classifier: License :: OSI Approved :: MIT License
Classifier: Programming Language :: Python :: 3
Requires-Python: >=3.8
